soccer/__init__.py
soccer/exceptions.py
soccer/leagueids.py
soccer/leagueproperties.py
soccer/main.py
soccer/teamnames.py
soccer/writers.py
soccer_cli-0.1.0.0.dist-info/DESCRIPTION.rst
soccer_cli-0.1.0.0.dist-info/METADATA
soccer_cli-0.1.0.0.dist-info/RECORD
soccer_cli-0.1.0.0.dist-info/WHEEL
soccer_cli-0.1.0.0.dist-info/entry_points.txt
soccer_cli-0.1.0.0.dist-info/metadata.json
soccer_cli-0.1.0.0.dist-info/top_level.txt
