Metadata-Version: 2.0
Name: soccer-cli
Version: 0.1.0.0
Summary: Soccer for Hackers.
Home-page: https://github.com/architv/soccer-cli
Author: Archit Verma
Author-email: architv07@gmail.com
License: MIT
Keywords: soccer football espn scores live tool cli
Platform: UNKNOWN
Classifier: Development Status :: 3 - Alpha
Classifier: Intended Audience :: Developers
Classifier: Topic :: Software Development :: Build Tools
Classifier: License :: OSI Approved :: MIT License
Classifier: Programming Language :: Python :: 2
Classifier: Programming Language :: Python :: 2.6
Classifier: Programming Language :: Python :: 2.7
Requires-Dist: click (>=5.0)
Requires-Dist: requests (==2.7.0)
